.gitignore
.pre-commit-config.yaml
README.md
pyproject.toml
requirements.txt
setup.cfg
setup.py
testbed.py
.github/workflows/CI.template
.github/workflows/CI.yml.disabled
.github/workflows/publish.yml
bijax/__init__.py
bijax/_version.py
bijax/advi.py
bijax/core.py
bijax/laplace.py
bijax/mcmc.py
bijax/utils.py
bijax.egg-info/PKG-INFO
bijax.egg-info/SOURCES.txt
bijax.egg-info/dependency_links.txt
bijax.egg-info/requires.txt
bijax.egg-info/top_level.txt
examples/advi/bayesian_neural_network.ipynb
examples/advi/coin_toss.ipynb
examples/advi/gaussian_mixture_model.ipynb
examples/advi/gp_classification.ipynb
examples/advi/neural_linear_model.ipynb
examples/mcmc/eight_schools_unfinished.ipynb