Metadata-Version: 2.1
Name: bijax
Version: 0.1.1
Summary: Approximate Bayesian Inference in JAX
Home-page: https://github.com/patel-zeel/bijax
Author: Zeel B Patel
Author-email: patel_zeel@iitgn.ac.in
License: MIT
Requires-Python: >=3.6
